isanlp_rst/__init__.py
isanlp_rst/base_predictor.py
isanlp_rst/parser.py
isanlp_rst/dmrst_parser/__init__.py
isanlp_rst/dmrst_parser/data_manager.py
isanlp_rst/dmrst_parser/multiple_runs.py
isanlp_rst/dmrst_parser/predictor.py
isanlp_rst/dmrst_parser/src/__init__.py
isanlp_rst/dmrst_parser/src/config_reader.py
isanlp_rst/dmrst_parser/src/corpus/__init__.py
isanlp_rst/dmrst_parser/src/corpus/binary_tree.py
isanlp_rst/dmrst_parser/src/corpus/common.py
isanlp_rst/dmrst_parser/src/corpus/data.py
isanlp_rst/dmrst_parser/src/corpus/relation_set.py
isanlp_rst/dmrst_parser/src/corpus/utils_dis_thiago.py
isanlp_rst/dmrst_parser/src/corpus/utils_rs3.py
isanlp_rst/dmrst_parser/src/parser/__init__.py
isanlp_rst/dmrst_parser/src/parser/bimpm.py
isanlp_rst/dmrst_parser/src/parser/data.py
isanlp_rst/dmrst_parser/src/parser/discriminator.py
isanlp_rst/dmrst_parser/src/parser/metrics.py
isanlp_rst/dmrst_parser/src/parser/modules.py
isanlp_rst/dmrst_parser/src/parser/parsing_net.py
isanlp_rst/dmrst_parser/src/parser/segmenters.py
isanlp_rst/dmrst_parser/src/parser/training_manager.py
isanlp_rst/rstviewer/__init__.py
isanlp_rst/rstviewer/main.py
isanlp_rst/rstviewer/rstweb_classes.py
isanlp_rst/rstviewer/rstweb_reader.py
isanlp_rst/rstviewer/rstweb_sql.py
isanlp_rst/rstviewer/data/css/rst.css
isanlp_rst/rstviewer/data/script/jquery-1.11.3.min.js
isanlp_rst/rstviewer/data/script/jquery-ui.min.css
isanlp_rst/rstviewer/data/script/jquery-ui.min.js
isanlp_rst/rstviewer/data/script/jquery.jsPlumb-1.7.5-min.js
isanlp_rst/rstviewer/data/script/structure.js
isanlp_rst/rstviewer/data/templates/main.html
isanlp_rst/tests/dmrst_test.py
isanlp_rst/tests/unirst_test.py
isanlp_rst/universal_parser/__init__.py
isanlp_rst/universal_parser/data_manager.py
isanlp_rst/universal_parser/multiple_runs.py
isanlp_rst/universal_parser/predictor.py
isanlp_rst/universal_parser/src/__init__.py
isanlp_rst/universal_parser/src/config_reader.py
isanlp_rst/universal_parser/src/corpus/__init__.py
isanlp_rst-3.2.0.dist-info/licenses/LICENSE
isanlp_rst-3.2.0.dist-info/licenses/LICENSE_MODELS
isanlp_rst-3.2.0.dist-info/METADATA
isanlp_rst-3.2.0.dist-info/WHEEL
isanlp_rst-3.2.0.dist-info/top_level.txt
isanlp_rst-3.2.0.dist-info/RECORD
