Metadata-Version: 2.4
Name: isanlp_rst
Version: 3.2.0
Summary: IsaNLP RST Parser: A library for parsing Rhetorical Structure Theory trees.
Author-email: Elena Chistova <elenachistov@gmail.com>
Project-URL: Homepage, https://github.com/tchewik/isanlp_rst
Requires-Python: >=3.8
License-File: LICENSE
License-File: LICENSE_MODELS
Requires-Dist: asyncio
Requires-Dist: playwright
Requires-Dist: razdel
Requires-Dist: fire
Requires-Dist: matplotlib
Requires-Dist: lxml
Requires-Dist: jsonnet
Requires-Dist: nltk
Requires-Dist: spacy
Requires-Dist: numpy==1.26.4
Requires-Dist: transformers
Requires-Dist: torch
Dynamic: license-file
